vbaspy/__init__.py
vbaspy/auth/__init__.py
vbaspy/auth/riot_auth/__init__.py
vbaspy/auth/riot_auth/auth.py
vbaspy/auth/riot_auth/auth_exceptions.py
vbaspy/vbasmian/__init__.py
vbaspy/vbasmian/src/__init__.py
vbaspy/vbasmian/src/idgenerator.py
vbaspy/vbasmian/src/utils.py
vbaspy/vbasmian/store/__init__.py
vbaspy/vbasmian/store/store.py
vbaspy/vbasmian/store/store_exceptions.py
vbaspy/vbasmian/test/__init__.py
vbaspy/vbasmian/test/mainapi.py
vbaspy-2.0.0.dist-info/METADATA
vbaspy-2.0.0.dist-info/WHEEL
vbaspy-2.0.0.dist-info/top_level.txt
vbaspy-2.0.0.dist-info/RECORD
