Metadata-Version: 2.1
Name: vbaspy
Version: 2.0.0
Summary: ValorantBot Api System
Home-page: https://github.com/KLDiscord/vbaspy
Author: DoubleEight
Author-email: fanta09tv@gmail.com
Classifier: Programming Language :: Python :: 3
Classifier: License :: OSI Approved :: MIT License
Classifier: Operating System :: OS Independent
Requires-Python: >=3.6
